evm_build/__init__.py
evm_build-0.1.5.dist-info/METADATA
evm_build-0.1.5.dist-info/WHEEL
evm_build-0.1.5.dist-info/top_level.txt
evm_build-0.1.5.dist-info/RECORD
